httpx_sap_launchpad/__init__.py
httpx_sap_launchpad/_auth.py
httpx_sap_launchpad/_constants.py
httpx_sap_launchpad/_exceptions.py
httpx_sap_launchpad/_html.py
httpx_sap_launchpad/_httpx.py
httpx_sap_launchpad/py.typed
httpx_sap_launchpad-0.1.1.dist-info/licenses/LICENSE.txt
httpx_sap_launchpad-0.1.1.dist-info/METADATA
httpx_sap_launchpad-0.1.1.dist-info/WHEEL
httpx_sap_launchpad-0.1.1.dist-info/top_level.txt
httpx_sap_launchpad-0.1.1.dist-info/RECORD
