Metadata-Version: 2.4
Name: httpx-sap-launchpad
Version: 0.1.1
Summary: httpx Authentication for the SAP Launchpad API
Project-URL: Source, https://github.com/whilenot-dev/httpx-sap-launchpad
Classifier: License :: OSI Approved :: MIT License
Classifier: Development Status :: 4 - Beta
Classifier: Framework :: AsyncIO
Classifier: Intended Audience :: Developers
Classifier: Programming Language :: Python :: 3.10
Classifier: Programming Language :: Python :: 3.11
Classifier: Programming Language :: Python :: 3.12
Classifier: Programming Language :: Python :: 3.13
Classifier: Programming Language :: Python :: 3 :: Only
Requires-Python: >=3.10
License-File: LICENSE.txt
Requires-Dist: beautifulsoup4>=4.13.5
Requires-Dist: httpx>=0.28.1
Dynamic: license-file
